ls_mcmc/__init__.py
ls_mcmc/algorithms.py
ls_mcmc/logging.py
ls_mcmc/model.py
ls_mcmc/output.py
ls_mcmc/py.typed
ls_mcmc/sampling.py
ls_mcmc/storage.py
ls_mcmc-0.0.3.dist-info/METADATA
ls_mcmc-0.0.3.dist-info/WHEEL
ls_mcmc-0.0.3.dist-info/licenses/LICENSE
ls_mcmc-0.0.3.dist-info/RECORD
