Metadata-Version: 2.4
Name: ls-mcmc
Version: 0.0.3
Summary: A light-weight library for large-scale Markov Chain Monte Carlo sampling
Project-URL: repository, https://github.com/UQatKIT/ls-mcmc
Author-email: Maximilian Kruse <maximilian.kruse@kit.edu>, Felix Racz <felix.racz@kit.edu>
Maintainer-email: Maximilian Kruse <maximilian.kruse@kit.edu>, Felix Racz <felix.racz@kit.edu>
License: MIT
License-File: LICENSE
Keywords: Bayesian inverse problems,large-scale,markov chain monte carlo
Classifier: Development Status :: 3 - Alpha
Classifier: Intended Audience :: Science/Research
Classifier: License :: OSI Approved :: MIT License
Classifier: Operating System :: POSIX :: Linux
Classifier: Programming Language :: Python :: 3
Requires-Python: >=3.12
Requires-Dist: numpy>=2.1.2
Requires-Dist: zarr>=3.0.1
